README.rst
setup.py
kamo/__init__.py
kamo/_sample.py
kamo/expr.py
kamo.egg-info/PKG-INFO
kamo.egg-info/SOURCES.txt
kamo.egg-info/dependency_links.txt
kamo.egg-info/entry_points.txt
kamo.egg-info/not-zip-safe
kamo.egg-info/requires.txt
kamo.egg-info/top_level.txt
kamo/tests/__init__.py
kamo/tests/test_compiler.py
kamo/tests/test_declared.py
kamo/tests/test_optimize.py