Metadata-Version: 1.1
Name: kamo
Version: 0.0
Summary: kamo is almost subset of mako, maybe
Home-page: https://github.com/podhmo/kamo
Author: podhmo
Author-email: UNKNOWN
License: UNKNOWN
Platform: UNKNOWN
Classifier: Programming Language :: Python
Classifier: Programming Language :: Python :: Implementation :: CPython
